assignable_users/__init__.py
assignable_users/get_assignable_users.py
create_jira_tickets/__init__.py
create_jira_tickets/create_fancy_jira_issue.py
create_jira_tickets/create_jira_epic.py
create_jira_tickets/create_jira_issue.py
create_jira_tickets/create_jira_issue_with_parent.py
emailer/__init__.py
emailer/aws_emailer/__init__.py
emailer/aws_emailer/email_with_attachment.py
emailer/gcp_emailer/__init__.py
emailer/gcp_emailer/gcp_email.py
JiraScripting_public-0.0.2.dist-info/LICENSE
JiraScripting_public-0.0.2.dist-info/METADATA
JiraScripting_public-0.0.2.dist-info/WHEEL
JiraScripting_public-0.0.2.dist-info/top_level.txt
JiraScripting_public-0.0.2.dist-info/RECORD
