Metadata-Version: 2.1
Name: JiraScripting-public
Version: 0.0.2
Summary: Methods for interacting with Jira Cloud
Author: David Renton
Author-email: <davidleerenton@gmail.com>
Keywords: python,first package
Classifier: Development Status :: 3 - Alpha
Classifier: Intended Audience :: Education
Classifier: Programming Language :: Python :: 3
Classifier: Operating System :: MacOS :: MacOS X
Classifier: Operating System :: Microsoft :: Windows
License-File: LICENSE
Requires-Dist: requests ~=2.23.0
Requires-Dist: python-dotenv ~=0.19.0
Requires-Dist: json
